bilibili/VERSION.txt
bilibili/__init__.py
bilibili/info.py
bilibili/m_mysql.py
bilibili/m_reque.py
bilibili/m_test.py
bilibili/user_bilibili.py
bilibili/video_bilibili.py
niconico-0.0.1.dist-info/METADATA
niconico-0.0.1.dist-info/RECORD
niconico-0.0.1.dist-info/WHEEL
niconico-0.0.1.dist-info/top_level.txt
